{
    "Loaded": true,
    "Name": "Damenaweyn",
    "RegionName": "Totambu",
    "HasDungeon": false,
    "MapTableData": {
        "MapId": 889574370,
        "Latitude": 15120,
        "Longitude": 118024,
        "LocationType": "TownCity",
        "DungeonType": "NoDungeon",
        "Discovered": true,
        "Key": 27787136
    },
    "Exterior": {
        "RecordElement": {
            "Header": {
                "X": 30214144,
                "Y": 3870721,
                "IsExterior": 32768,
                "Unknown2": 848,
                "LocationId": 26031,
                "IsInterior": 0,
                "ExteriorLocationId": 0,
                "LocationName": "Damenaweyn"
            }
        },
        "BuildingCount": 388,
        "Buildings": [
            {
                "NameSeed": 18751,
                "FactionId": 0,
                "Sector": 97,
                "LocationId": 26031,
                "BuildingType": "House2",
                "Quality": 16
            },
            {
                "FactionId": 0,
                "BuildingType": 23,
                "Quality": 7,
                "NameSeed": 16243,
                "Sector": 4,
                "LocationId": 26031
            },
            {
                "FactionId": 0,
                "BuildingType": 23,
                "Quality": 14,
                "NameSeed": 28925,
                "Sector": 7,
                "LocationId": 26031
            },
            {
                "FactionId": 0,
                "BuildingType": 23,
                "Quality": 18,
                "NameSeed": 5844,
                "Sector": 9,
                "LocationId": 26031
            },
            {
                "FactionId": 0,
                "BuildingType": 23,
                "Quality": 5,
                "NameSeed": 15992,
                "Sector": 11,
                "LocationId": 26031
            },
            {
                "FactionId": 0,
                "BuildingType": 23,
                "Quality": 11,
                "NameSeed": 19370,
                "Sector": 13,
                "LocationId": 26031
            },
            {
                "FactionId": 0,
                "BuildingType": 23,
                "Quality": 6,
                "NameSeed": 10956,
                "Sector": 16,
                "LocationId": 26031
            },
            {
                "FactionId": 0,
                "BuildingType": 23,
                "Quality": 12,
                "NameSeed": 26876,
                "Sector": 18,
                "LocationId": 26031
            },
            {
                "FactionId": 0,
                "BuildingType": 23,
                "Quality": 5,
                "NameSeed": 6714,
                "Sector": 20,
                "LocationId": 26031
            },
            {
                "FactionId": 0,
                "BuildingType": 23,
                "Quality": 19,
                "NameSeed": 18874,
                "Sector": 22,
                "LocationId": 26031
            },
            {
                "FactionId": 0,
                "BuildingType": 15,
                "Quality": 10,
                "NameSeed": 20800,
                "Sector": 80,
                "LocationId": 26031
            },
            {
                "FactionId": 0,
                "BuildingType": 15,
                "Quality": 12,
                "NameSeed": 16100,
                "Sector": 166,
                "LocationId": 26031
            },
            {
                "FactionId": 0,
                "BuildingType": 15,
                "Quality": 16,
                "NameSeed": 21961,
                "Sector": 237,
                "LocationId": 26031
            },
            {
                "NameSeed": 7773,
                "FactionId": 0,
                "Sector": 124,
                "LocationId": 26031,
                "BuildingType": "House3",
                "Quality": 17
            },
            {
                "NameSeed": 2561,
                "FactionId": 0,
                "Sector": 108,
                "LocationId": 26031,
                "BuildingType": "House2",
                "Quality": 9
            },
            {
                "NameSeed": 5603,
                "FactionId": 0,
                "Sector": 111,
                "LocationId": 26031,
                "BuildingType": "House2",
                "Quality": 10
            },
            {
                "NameSeed": 6354,
                "FactionId": 0,
                "Sector": 135,
                "LocationId": 26031,
                "BuildingType": "House2",
                "Quality": 13
            },
            {
                "NameSeed": 11454,
                "FactionId": 0,
                "Sector": 157,
                "LocationId": 26031,
                "BuildingType": "House2",
                "Quality": 11
            },
            {
                "NameSeed": 23488,
                "FactionId": 0,
                "Sector": 129,
                "LocationId": 26031,
                "BuildingType": "House3",
                "Quality": 20
            },
            {
                "NameSeed": 31821,
                "FactionId": 0,
                "Sector": 160,
                "LocationId": 26031,
                "BuildingType": "House2",
                "Quality": 7
            },
            {
                "FactionId": 0,
                "BuildingType": 23,
                "Quality": 6,
                "NameSeed": 2611,
                "Sector": 25,
                "LocationId": 26031
            },
            {
                "FactionId": 0,
                "BuildingType": 23,
                "Quality": 6,
                "NameSeed": 3008,
                "Sector": 27,
                "LocationId": 26031
            },
            {
                "FactionId": 0,
                "BuildingType": 23,
                "Quality": 10,
                "NameSeed": 21177,
                "Sector": 29,
                "LocationId": 26031
            },
            {
                "FactionId": 0,
                "BuildingType": 23,
                "Quality": 7,
                "NameSeed": 13963,
                "Sector": 31,
                "LocationId": 26031
            },
            {
                "NameSeed": 29229,
                "FactionId": 0,
                "Sector": 201,
                "LocationId": 26031,
                "BuildingType": "House2",
                "Quality": 14
            },
            {
                "FactionId": 0,
                "BuildingType": 23,
                "Quality": 6,
                "NameSeed": 8566,
                "Sector": 34,
                "LocationId": 26031
            },
            {
                "FactionId": 0,
                "BuildingType": 23,
                "Quality": 12,
                "NameSeed": 4537,
                "Sector": 36,
                "LocationId": 26031
            },
            {
                "FactionId": 0,
                "BuildingType": 23,
                "Quality": 18,
                "NameSeed": 2713,
                "Sector": 38,
                "LocationId": 26031
            },
            {
                "FactionId": 0,
                "BuildingType": 23,
                "Quality": 11,
                "NameSeed": 26434,
                "Sector": 40,
                "LocationId": 26031
            },
            {
                "FactionId": 0,
                "BuildingType": 23,
                "Quality": 7,
                "NameSeed": 19316,
                "Sector": 43,
                "LocationId": 26031
            },
            {
                "NameSeed": 19646,
                "FactionId": 0,
                "Sector": 221,
                "LocationId": 26031,
                "BuildingType": "House2",
                "Quality": 18
            },
            {
                "FactionId": 0,
                "BuildingType": 23,
                "Quality": 8,
                "NameSeed": 11641,
                "Sector": 45,
                "LocationId": 26031
            },
            {
                "NameSeed": 24959,
                "FactionId": 0,
                "Sector": 232,
                "LocationId": 26031,
                "BuildingType": "House2",
                "Quality": 10
            },
            {
                "NameSeed": 22078,
                "FactionId": 0,
                "Sector": 1628,
                "LocationId": 26031,
                "BuildingType": "House5",
                "Quality": 10
            },
            {
                "NameSeed": 19015,
                "FactionId": 0,
                "Sector": 1631,
                "LocationId": 26031,
                "BuildingType": "House5",
                "Quality": 10
            },
            {
                "FactionId": 0,
                "BuildingType": 23,
                "Quality": 5,
                "NameSeed": 6870,
                "Sector": 47,
                "LocationId": 26031
            },
            {
                "FactionId": 0,
                "BuildingType": 23,
                "Quality": 14,
                "NameSeed": 21696,
                "Sector": 49,
                "LocationId": 26031
            },
            {
                "FactionId": 0,
                "BuildingType": 23,
                "Quality": 7,
                "NameSeed": 9002,
                "Sector": 52,
                "LocationId": 26031
            },
            {
                "FactionId": 0,
                "BuildingType": 23,
                "Quality": 14,
                "NameSeed": 13582,
                "Sector": 55,
                "LocationId": 26031
            },
            {
                "FactionId": 0,
                "BuildingType": 23,
                "Quality": 8,
                "NameSeed": 588,
                "Sector": 57,
                "LocationId": 26031
            },
            {
                "FactionId": 0,
                "BuildingType": 23,
                "Quality": 11,
                "NameSeed": 22306,
                "Sector": 59,
                "LocationId": 26031
            },
            {
                "FactionId": 0,
                "BuildingType": 23,
                "Quality": 18,
                "NameSeed": 27439,
                "Sector": 61,
                "LocationId": 26031
            },
            {
                "NameSeed": 4569,
                "FactionId": 0,
                "Sector": 270,
                "LocationId": 26031,
                "BuildingType": "House2",
                "Quality": 9
            },
            {
                "NameSeed": 7543,
                "FactionId": 0,
                "Sector": 274,
                "LocationId": 26031,
                "BuildingType": "House2",
                "Quality": 11
            },
            {
                "NameSeed": 5513,
                "FactionId": 0,
                "Sector": 376,
                "LocationId": 26031,
                "BuildingType": "House3",
                "Quality": 9
            },
            {
                "NameSeed": 21507,
                "FactionId": 0,
                "Sector": 279,
                "LocationId": 26031,
                "BuildingType": "House2",
                "Quality": 9
            },
            {
                "NameSeed": 20067,
                "FactionId": 0,
                "Sector": 292,
                "LocationId": 26031,
                "BuildingType": "House2",
                "Quality": 14
            },
            {
                "NameSeed": 25364,
                "FactionId": 0,
                "Sector": 303,
                "LocationId": 26031,
                "BuildingType": "House2",
                "Quality": 10
            },
            {
                "FactionId": 0,
                "BuildingType": 18,
                "Quality": 12,
                "NameSeed": 13280,
                "Sector": 332,
                "LocationId": 26031
            },
            {
                "NameSeed": 9879,
                "FactionId": 0,
                "Sector": 349,
                "LocationId": 26031,
                "BuildingType": "House2",
                "Quality": 17
            },
            {
                "NameSeed": 16917,
                "FactionId": 0,
                "Sector": 517,
                "LocationId": 26031,
                "BuildingType": "House3",
                "Quality": 20
            },
            {
                "FactionId": 0,
                "BuildingType": 18,
                "Quality": 12,
                "NameSeed": 20281,
                "Sector": 358,
                "LocationId": 26031
            },
            {
                "NameSeed": 20944,
                "FactionId": 0,
                "Sector": 363,
                "LocationId": 26031,
                "BuildingType": "House2",
                "Quality": 7
            },
            {
                "NameSeed": 16969,
                "FactionId": 0,
                "Sector": 385,
                "LocationId": 26031,
                "BuildingType": "House2",
                "Quality": 17
            },
            {
                "NameSeed": 1083,
                "FactionId": 0,
                "Sector": 395,
                "LocationId": 26031,
                "BuildingType": "House2",
                "Quality": 9
            },
            {
                "FactionId": 0,
                "BuildingType": 18,
                "Quality": 7,
                "NameSeed": 3472,
                "Sector": 403,
                "LocationId": 26031
            },
            {
                "NameSeed": 27488,
                "FactionId": 0,
                "Sector": 407,
                "LocationId": 26031,
                "BuildingType": "House2",
                "Quality": 12
            },
            {
                "FactionId": 0,
                "BuildingType": 15,
                "Quality": 19,
                "NameSeed": 25646,
                "Sector": 541,
                "LocationId": 26031
            },
            {
                "FactionId": 0,
                "BuildingType": 15,
                "Quality": 8,
                "NameSeed": 14012,
                "Sector": 610,
                "LocationId": 26031
            },
            {
                "FactionId": 0,
                "BuildingType": 19,
                "Quality": 18,
                "NameSeed": 753,
                "Sector": 681,
                "LocationId": 26031
            },
            {
                "NameSeed": 19229,
                "FactionId": 0,
                "Sector": 411,
                "LocationId": 26031,
                "BuildingType": "House2",
                "Quality": 19
            },
            {
                "FactionId": 0,
                "BuildingType": 18,
                "Quality": 11,
                "NameSeed": 580,
                "Sector": 424,
                "LocationId": 26031
            },
            {
                "NameSeed": 32520,
                "FactionId": 0,
                "Sector": 466,
                "LocationId": 26031,
                "BuildingType": "House2",
                "Quality": 19
            },
            {
                "NameSeed": 14195,
                "FactionId": 0,
                "Sector": 1386,
                "LocationId": 26031,
                "BuildingType": "House3",
                "Quality": 10
            },
            {
                "NameSeed": 13186,
                "FactionId": 0,
                "Sector": 469,
                "LocationId": 26031,
                "BuildingType": "House2",
                "Quality": 16
            },
            {
                "NameSeed": 1304,
                "FactionId": 0,
                "Sector": 480,
                "LocationId": 26031,
                "BuildingType": "House2",
                "Quality": 8
            },
            {
                "NameSeed": 9875,
                "FactionId": 0,
                "Sector": 484,
                "LocationId": 26031,
                "BuildingType": "House2",
                "Quality": 17
            },
            {
                "NameSeed": 28435,
                "FactionId": 0,
                "Sector": 511,
                "LocationId": 26031,
                "BuildingType": "House2",
                "Quality": 5
            },
            {
                "NameSeed": 22537,
                "FactionId": 0,
                "Sector": 522,
                "LocationId": 26031,
                "BuildingType": "House2",
                "Quality": 9
            },
            {
                "NameSeed": 8989,
                "FactionId": 0,
                "Sector": 557,
                "LocationId": 26031,
                "BuildingType": "House2",
                "Quality": 5
            },
            {
                "NameSeed": 16095,
                "FactionId": 0,
                "Sector": 564,
                "LocationId": 26031,
                "BuildingType": "House2",
                "Quality": 11
            },
            {
                "NameSeed": 9361,
                "FactionId": 0,
                "Sector": 570,
                "LocationId": 26031,
                "BuildingType": "House2",
                "Quality": 13
            },
            {
                "NameSeed": 23898,
                "FactionId": 0,
                "Sector": 577,
                "LocationId": 26031,
                "BuildingType": "House2",
                "Quality": 9
            },
            {
                "NameSeed": 15950,
                "FactionId": 0,
                "Sector": 595,
                "LocationId": 26031,
                "BuildingType": "House2",
                "Quality": 11
            },
            {
                "NameSeed": 24387,
                "FactionId": 0,
                "Sector": 634,
                "LocationId": 26031,
                "BuildingType": "House2",
                "Quality": 6
            },
            {
                "NameSeed": 1509,
                "FactionId": 22,
                "Sector": 432,
                "LocationId": 26031,
                "BuildingType": "Temple",
                "Quality": 8
            },
            {
                "NameSeed": 24889,
                "FactionId": 0,
                "Sector": 645,
                "LocationId": 26031,
                "BuildingType": "House2",
                "Quality": 15
            },
            {
                "NameSeed": 387,
                "FactionId": 0,
                "Sector": 652,
                "LocationId": 26031,
                "BuildingType": "House2",
                "Quality": 18
            },
            {
                "NameSeed": 4941,
                "FactionId": 0,
                "Sector": 666,
                "LocationId": 26031,
                "BuildingType": "House2",
                "Quality": 6
            },
            {
                "NameSeed": 2558,
                "FactionId": 0,
                "Sector": 694,
                "LocationId": 26031,
                "BuildingType": "House2",
                "Quality": 16
            },
            {
                "NameSeed": 18842,
                "FactionId": 0,
                "Sector": 701,
                "LocationId": 26031,
                "BuildingType": "House2",
                "Quality": 7
            },
            {
                "NameSeed": 29818,
                "FactionId": 0,
                "Sector": 705,
                "LocationId": 26031,
                "BuildingType": "House2",
                "Quality": 9
            },
            {
                "NameSeed": 31762,
                "FactionId": 0,
                "Sector": 712,
                "LocationId": 26031,
                "BuildingType": "House2",
                "Quality": 12
            },
            {
                "FactionId": 0,
                "BuildingType": 15,
                "Quality": 13,
                "NameSeed": 144,
                "Sector": 754,
                "LocationId": 26031
            },
            {
                "NameSeed": 2052,
                "FactionId": 0,
                "Sector": 720,
                "LocationId": 26031,
                "BuildingType": "House2",
                "Quality": 12
            },
            {
                "NameSeed": 15547,
                "FactionId": 0,
                "Sector": 730,
                "LocationId": 26031,
                "BuildingType": "House2",
                "Quality": 13
            },
            {
                "NameSeed": 7524,
                "FactionId": 0,
                "Sector": 743,
                "LocationId": 26031,
                "BuildingType": "House2",
                "Quality": 18
            },
            {
                "NameSeed": 19739,
                "FactionId": 0,
                "Sector": 782,
                "LocationId": 26031,
                "BuildingType": "House2",
                "Quality": 18
            },
            {
                "NameSeed": 20433,
                "FactionId": 0,
                "Sector": 794,
                "LocationId": 26031,
                "BuildingType": "House2",
                "Quality": 13
            },
            {
                "NameSeed": 1780,
                "FactionId": 0,
                "Sector": 805,
                "LocationId": 26031,
                "BuildingType": "House2",
                "Quality": 19
            },
            {
                "NameSeed": 4450,
                "FactionId": 0,
                "Sector": 811,
                "LocationId": 26031,
                "BuildingType": "House2",
                "Quality": 7
            },
            {
                "NameSeed": 25472,
                "FactionId": 0,
                "Sector": 816,
                "LocationId": 26031,
                "BuildingType": "House2",
                "Quality": 18
            },
            {
                "FactionId": 0,
                "BuildingType": 18,
                "Quality": 12,
                "NameSeed": 27874,
                "Sector": 829,
                "LocationId": 26031
            },
            {
                "NameSeed": 22233,
                "FactionId": 0,
                "Sector": 873,
                "LocationId": 26031,
                "BuildingType": "House2",
                "Quality": 10
            },
            {
                "FactionId": 0,
                "BuildingType": 8,
                "Quality": 12,
                "NameSeed": 22000,
                "Sector": 1218,
                "LocationId": 26031
            },
            {
                "NameSeed": 11003,
                "FactionId": 0,
                "Sector": 878,
                "LocationId": 26031,
                "BuildingType": "House2",
                "Quality": 13
            },
            {
                "NameSeed": 24884,
                "FactionId": 0,
                "Sector": 884,
                "LocationId": 26031,
                "BuildingType": "House2",
                "Quality": 19
            },
            {
                "NameSeed": 32738,
                "FactionId": 0,
                "Sector": 891,
                "LocationId": 26031,
                "BuildingType": "House2",
                "Quality": 19
            },
            {
                "NameSeed": 8513,
                "FactionId": 0,
                "Sector": 909,
                "LocationId": 26031,
                "BuildingType": "House2",
                "Quality": 5
            },
            {
                "NameSeed": 12968,
                "FactionId": 0,
                "Sector": 915,
                "LocationId": 26031,
                "BuildingType": "House2",
                "Quality": 12
            },
            {
                "NameSeed": 9125,
                "FactionId": 0,
                "Sector": 926,
                "LocationId": 26031,
                "BuildingType": "House2",
                "Quality": 5
            },
            {
                "NameSeed": 10510,
                "FactionId": 0,
                "Sector": 930,
                "LocationId": 26031,
                "BuildingType": "House2",
                "Quality": 11
            },
            {
                "NameSeed": 15817,
                "FactionId": 0,
                "Sector": 935,
                "LocationId": 26031,
                "BuildingType": "House2",
                "Quality": 10
            },
            {
                "NameSeed": 31881,
                "FactionId": 0,
                "Sector": 962,
                "LocationId": 26031,
                "BuildingType": "House2",
                "Quality": 20
            },
            {
                "NameSeed": 20866,
                "FactionId": 0,
                "Sector": 990,
                "LocationId": 26031,
                "BuildingType": "House2",
                "Quality": 18
            },
            {
                "NameSeed": 6601,
                "FactionId": 0,
                "Sector": 995,
                "LocationId": 26031,
                "BuildingType": "House2",
                "Quality": 14
            },
            {
                "NameSeed": 29226,
                "FactionId": 0,
                "Sector": 999,
                "LocationId": 26031,
                "BuildingType": "House2",
                "Quality": 5
            },
            {
                "NameSeed": 1675,
                "FactionId": 0,
                "Sector": 1008,
                "LocationId": 26031,
                "BuildingType": "House2",
                "Quality": 9
            },
            {
                "NameSeed": 7243,
                "FactionId": 0,
                "Sector": 1017,
                "LocationId": 26031,
                "BuildingType": "House2",
                "Quality": 18
            },
            {
                "NameSeed": 7751,
                "FactionId": 0,
                "Sector": 1021,
                "LocationId": 26031,
                "BuildingType": "House2",
                "Quality": 8
            },
            {
                "NameSeed": 11981,
                "FactionId": 0,
                "Sector": 940,
                "LocationId": 26031,
                "BuildingType": "Tavern",
                "Quality": 5
            },
            {
                "NameSeed": 18421,
                "FactionId": 42,
                "Sector": 1026,
                "LocationId": 26031,
                "BuildingType": "House2",
                "Quality": 8
            },
            {
                "FactionId": 0,
                "BuildingType": 23,
                "Quality": 7,
                "NameSeed": 30956,
                "Sector": 448,
                "LocationId": 26031
            },
            {
                "FactionId": 0,
                "BuildingType": 23,
                "Quality": 7,
                "NameSeed": 24260,
                "Sector": 450,
                "LocationId": 26031
            },
            {
                "FactionId": 0,
                "BuildingType": 23,
                "Quality": 11,
                "NameSeed": 2233,
                "Sector": 452,
                "LocationId": 26031
            },
            {
                "FactionId": 0,
                "BuildingType": 23,
                "Quality": 6,
                "NameSeed": 11398,
                "Sector": 454,
                "LocationId": 26031
            },
            {
                "FactionId": 0,
                "BuildingType": 23,
                "Quality": 18,
                "NameSeed": 2161,
                "Sector": 457,
                "LocationId": 26031
            },
            {
                "FactionId": 0,
                "BuildingType": 23,
                "Quality": 20,
                "NameSeed": 1716,
                "Sector": 459,
                "LocationId": 26031
            },
            {
                "FactionId": 0,
                "BuildingType": 23,
                "Quality": 8,
                "NameSeed": 13489,
                "Sector": 461,
                "LocationId": 26031
            },
            {
                "FactionId": 0,
                "BuildingType": 23,
                "Quality": 12,
                "NameSeed": 25360,
                "Sector": 463,
                "LocationId": 26031
            },
            {
                "NameSeed": 24693,
                "FactionId": 0,
                "Sector": 151,
                "LocationId": 26031,
                "BuildingType": "Armorer",
                "Quality": 8
            },
            {
                "NameSeed": 12860,
                "FactionId": 0,
                "Sector": 1041,
                "LocationId": 26031,
                "BuildingType": "House2",
                "Quality": 8
            },
            {
                "NameSeed": 26669,
                "FactionId": 0,
                "Sector": 1163,
                "LocationId": 26031,
                "BuildingType": "House2",
                "Quality": 18
            },
            {
                "NameSeed": 1108,
                "FactionId": 0,
                "Sector": 1176,
                "LocationId": 26031,
                "BuildingType": "House2",
                "Quality": 18
            },
            {
                "NameSeed": 8852,
                "FactionId": 0,
                "Sector": 1194,
                "LocationId": 26031,
                "BuildingType": "House2",
                "Quality": 15
            },
            {
                "NameSeed": 13427,
                "FactionId": 0,
                "Sector": 1029,
                "LocationId": 26031,
                "BuildingType": "Tavern",
                "Quality": 13
            },
            {
                "NameSeed": 26361,
                "FactionId": 0,
                "Sector": 1202,
                "LocationId": 26031,
                "BuildingType": "House2",
                "Quality": 7
            },
            {
                "NameSeed": 31087,
                "FactionId": 0,
                "Sector": 1207,
                "LocationId": 26031,
                "BuildingType": "House2",
                "Quality": 12
            },
            {
                "NameSeed": 13357,
                "FactionId": 0,
                "Sector": 1231,
                "LocationId": 26031,
                "BuildingType": "House2",
                "Quality": 5
            },
            {
                "NameSeed": 3679,
                "FactionId": 0,
                "Sector": 1238,
                "LocationId": 26031,
                "BuildingType": "House2",
                "Quality": 7
            },
            {
                "NameSeed": 27436,
                "FactionId": 0,
                "Sector": 1249,
                "LocationId": 26031,
                "BuildingType": "House2",
                "Quality": 5
            },
            {
                "NameSeed": 18660,
                "FactionId": 0,
                "Sector": 1259,
                "LocationId": 26031,
                "BuildingType": "House2",
                "Quality": 15
            },
            {
                "NameSeed": 12781,
                "FactionId": 0,
                "Sector": 1282,
                "LocationId": 26031,
                "BuildingType": "House2",
                "Quality": 7
            },
            {
                "NameSeed": 6289,
                "FactionId": 0,
                "Sector": 1359,
                "LocationId": 26031,
                "BuildingType": "House2",
                "Quality": 14
            },
            {
                "NameSeed": 13843,
                "FactionId": 0,
                "Sector": 1366,
                "LocationId": 26031,
                "BuildingType": "House2",
                "Quality": 9
            },
            {
                "NameSeed": 23069,
                "FactionId": 0,
                "Sector": 1370,
                "LocationId": 26031,
                "BuildingType": "House2",
                "Quality": 12
            },
            {
                "NameSeed": 17318,
                "FactionId": 0,
                "Sector": 1105,
                "LocationId": 26031,
                "BuildingType": "Tavern",
                "Quality": 19
            },
            {
                "NameSeed": 6001,
                "FactionId": 0,
                "Sector": 1375,
                "LocationId": 26031,
                "BuildingType": "House2",
                "Quality": 16
            },
            {
                "NameSeed": 28603,
                "FactionId": 0,
                "Sector": 1381,
                "LocationId": 26031,
                "BuildingType": "House2",
                "Quality": 18
            },
            {
                "NameSeed": 32398,
                "FactionId": 0,
                "Sector": 1536,
                "LocationId": 26031,
                "BuildingType": "House3",
                "Quality": 18
            },
            {
                "NameSeed": 13784,
                "FactionId": 0,
                "Sector": 1397,
                "LocationId": 26031,
                "BuildingType": "House2",
                "Quality": 8
            },
            {
                "NameSeed": 7230,
                "FactionId": 0,
                "Sector": 1403,
                "LocationId": 26031,
                "BuildingType": "House2",
                "Quality": 6
            },
            {
                "NameSeed": 21911,
                "FactionId": 0,
                "Sector": 1448,
                "LocationId": 26031,
                "BuildingType": "House2",
                "Quality": 13
            },
            {
                "NameSeed": 28712,
                "FactionId": 0,
                "Sector": 1459,
                "LocationId": 26031,
                "BuildingType": "House2",
                "Quality": 6
            },
            {
                "NameSeed": 15971,
                "FactionId": 0,
                "Sector": 1468,
                "LocationId": 26031,
                "BuildingType": "House2",
                "Quality": 16
            },
            {
                "NameSeed": 28199,
                "FactionId": 0,
                "Sector": 1493,
                "LocationId": 26031,
                "BuildingType": "House2",
                "Quality": 14
            },
            {
                "NameSeed": 30673,
                "FactionId": 0,
                "Sector": 190,
                "LocationId": 26031,
                "BuildingType": "HouseForSale",
                "Quality": 11
            },
            {
                "NameSeed": 20470,
                "FactionId": 0,
                "Sector": 1545,
                "LocationId": 26031,
                "BuildingType": "House2",
                "Quality": 5
            },
            {
                "NameSeed": 31672,
                "FactionId": 0,
                "Sector": 1552,
                "LocationId": 26031,
                "BuildingType": "House2",
                "Quality": 11
            },
            {
                "NameSeed": 9107,
                "FactionId": 0,
                "Sector": 1558,
                "LocationId": 26031,
                "BuildingType": "House2",
                "Quality": 17
            },
            {
                "NameSeed": 10598,
                "FactionId": 0,
                "Sector": 1562,
                "LocationId": 26031,
                "BuildingType": "House2",
                "Quality": 18
            },
            {
                "NameSeed": 18347,
                "FactionId": 0,
                "Sector": 1634,
                "LocationId": 26031,
                "BuildingType": "House2",
                "Quality": 9
            },
            {
                "NameSeed": 28866,
                "FactionId": 41,
                "Sector": 602,
                "LocationId": 26031,
                "BuildingType": "GuildHall",
                "Quality": 17
            },
            {
                "FactionId": 0,
                "BuildingType": 18,
                "Quality": 6,
                "NameSeed": 27812,
                "Sector": 1637,
                "LocationId": 26031
            },
            {
                "NameSeed": 930,
                "FactionId": 0,
                "Sector": 1640,
                "LocationId": 26031,
                "BuildingType": "House3",
                "Quality": 6
            },
            {
                "NameSeed": 8428,
                "FactionId": 0,
                "Sector": 1643,
                "LocationId": 26031,
                "BuildingType": "House3",
                "Quality": 6
            },
            {
                "NameSeed": 29062,
                "FactionId": 0,
                "Sector": 1646,
                "LocationId": 26031,
                "BuildingType": "House2",
                "Quality": 6
            },
            {
                "NameSeed": 5657,
                "FactionId": 0,
                "Sector": 1649,
                "LocationId": 26031,
                "BuildingType": "House2",
                "Quality": 4
            },
            {
                "NameSeed": 18833,
                "FactionId": 0,
                "Sector": 1652,
                "LocationId": 26031,
                "BuildingType": "House3",
                "Quality": 6
            },
            {
                "NameSeed": 21670,
                "FactionId": 0,
                "Sector": 1655,
                "LocationId": 26031,
                "BuildingType": "House2",
                "Quality": 4
            },
            {
                "NameSeed": 8617,
                "FactionId": 0,
                "Sector": 1658,
                "LocationId": 26031,
                "BuildingType": "House2",
                "Quality": 5
            },
            {
                "NameSeed": 1052,
                "FactionId": 0,
                "Sector": 1661,
                "LocationId": 26031,
                "BuildingType": "House2",
                "Quality": 5
            },
            {
                "NameSeed": 831,
                "FactionId": 0,
                "Sector": 1664,
                "LocationId": 26031,
                "BuildingType": "House2",
                "Quality": 6
            },
            {
                "NameSeed": 27414,
                "FactionId": 0,
                "Sector": 1667,
                "LocationId": 26031,
                "BuildingType": "House2",
                "Quality": 4
            },
            {
                "NameSeed": 19206,
                "FactionId": 0,
                "Sector": 1670,
                "LocationId": 26031,
                "BuildingType": "House2",
                "Quality": 5
            },
            {
                "NameSeed": 14313,
                "FactionId": 0,
                "Sector": 1673,
                "LocationId": 26031,
                "BuildingType": "House2",
                "Quality": 6
            },
            {
                "NameSeed": 14916,
                "FactionId": 0,
                "Sector": 1676,
                "LocationId": 26031,
                "BuildingType": "House2",
                "Quality": 4
            },
            {
                "FactionId": 0,
                "BuildingType": 18,
                "Quality": 8,
                "NameSeed": 24402,
                "Sector": 1679,
                "LocationId": 26031
            },
            {
                "NameSeed": 12751,
                "FactionId": 0,
                "Sector": 1682,
                "LocationId": 26031,
                "BuildingType": "House3",
                "Quality": 4
            },
            {
                "NameSeed": 23057,
                "FactionId": 0,
                "Sector": 1685,
                "LocationId": 26031,
                "BuildingType": "House2",
                "Quality": 5
            },
            {
                "NameSeed": 11232,
                "FactionId": 0,
                "Sector": 1688,
                "LocationId": 26031,
                "BuildingType": "House2",
                "Quality": 6
            },
            {
                "NameSeed": 20481,
                "FactionId": 510,
                "Sector": 842,
                "LocationId": 26031,
                "BuildingType": "GeneralStore",
                "Quality": 15
            },
            {
                "NameSeed": 30985,
                "FactionId": 852,
                "Sector": 1473,
                "LocationId": 26031,
                "BuildingType": "Palace",
                "Quality": 6
            },
            {
                "NameSeed": 19958,
                "FactionId": 0,
                "Sector": 1691,
                "LocationId": 26031,
                "BuildingType": "House2",
                "Quality": 4
            },
            {
                "NameSeed": 9674,
                "FactionId": 0,
                "Sector": 1694,
                "LocationId": 26031,
                "BuildingType": "House2",
                "Quality": 6
            },
            {
                "NameSeed": 9662,
                "FactionId": 0,
                "Sector": 1697,
                "LocationId": 26031,
                "BuildingType": "House2",
                "Quality": 4
            },
            {
                "NameSeed": 12088,
                "FactionId": 0,
                "Sector": 1700,
                "LocationId": 26031,
                "BuildingType": "House2",
                "Quality": 4
            },
            {
                "NameSeed": 2560,
                "FactionId": 0,
                "Sector": 1703,
                "LocationId": 26031,
                "BuildingType": "House2",
                "Quality": 7
            },
            {
                "NameSeed": 7240,
                "FactionId": 0,
                "Sector": 1706,
                "LocationId": 26031,
                "BuildingType": "House2",
                "Quality": 4
            },
            {
                "NameSeed": 8871,
                "FactionId": 0,
                "Sector": 1709,
                "LocationId": 26031,
                "BuildingType": "House2",
                "Quality": 7
            },
            {
                "NameSeed": 23393,
                "FactionId": 0,
                "Sector": 1712,
                "LocationId": 26031,
                "BuildingType": "House2",
                "Quality": 8
            },
            {
                "NameSeed": 5425,
                "FactionId": 0,
                "Sector": 1715,
                "LocationId": 26031,
                "BuildingType": "House2",
                "Quality": 4
            },
            {
                "NameSeed": 8044,
                "FactionId": 0,
                "Sector": 1718,
                "LocationId": 26031,
                "BuildingType": "House2",
                "Quality": 6
            },
            {
                "NameSeed": 17320,
                "FactionId": 0,
                "Sector": 1721,
                "LocationId": 26031,
                "BuildingType": "House2",
                "Quality": 8
            },
            {
                "NameSeed": 5614,
                "FactionId": 0,
                "Sector": 1724,
                "LocationId": 26031,
                "BuildingType": "House2",
                "Quality": 5
            },
            {
                "NameSeed": 9604,
                "FactionId": 0,
                "Sector": 1727,
                "LocationId": 26031,
                "BuildingType": "House2",
                "Quality": 5
            },
            {
                "NameSeed": 11982,
                "FactionId": 0,
                "Sector": 1730,
                "LocationId": 26031,
                "BuildingType": "House2",
                "Quality": 3
            },
            {
                "FactionId": 0,
                "BuildingType": 18,
                "Quality": 4,
                "NameSeed": 28815,
                "Sector": 1733,
                "LocationId": 26031
            },
            {
                "NameSeed": 24764,
                "FactionId": 0,
                "Sector": 1736,
                "LocationId": 26031,
                "BuildingType": "House2",
                "Quality": 6
            },
            {
                "NameSeed": 25887,
                "FactionId": 0,
                "Sector": 1739,
                "LocationId": 26031,
                "BuildingType": "House2",
                "Quality": 7
            },
            {
                "NameSeed": 25974,
                "FactionId": 0,
                "Sector": 1742,
                "LocationId": 26031,
                "BuildingType": "House2",
                "Quality": 7
            },
            {
                "FactionId": 0,
                "BuildingType": 15,
                "Quality": 10,
                "NameSeed": 11222,
                "Sector": 1126,
                "LocationId": 26031
            },
            {
                "FactionId": 416,
                "BuildingType": 11,
                "Quality": 14,
                "NameSeed": 4628,
                "Sector": 766,
                "LocationId": 26031
            },
            {
                "FactionId": 0,
                "BuildingType": 23,
                "Quality": 11,
                "NameSeed": 28430,
                "Sector": 854,
                "LocationId": 26031
            },
            {
                "FactionId": 0,
                "BuildingType": 23,
                "Quality": 12,
                "NameSeed": 15459,
                "Sector": 856,
                "LocationId": 26031
            },
            {
                "FactionId": 0,
                "BuildingType": 23,
                "Quality": 10,
                "NameSeed": 15874,
                "Sector": 858,
                "LocationId": 26031
            },
            {
                "FactionId": 0,
                "BuildingType": 23,
                "Quality": 8,
                "NameSeed": 15304,
                "Sector": 860,
                "LocationId": 26031
            },
            {
                "FactionId": 0,
                "BuildingType": 23,
                "Quality": 19,
                "NameSeed": 17991,
                "Sector": 863,
                "LocationId": 26031
            },
            {
                "FactionId": 0,
                "BuildingType": 23,
                "Quality": 15,
                "NameSeed": 2475,
                "Sector": 865,
                "LocationId": 26031
            },
            {
                "FactionId": 0,
                "BuildingType": 23,
                "Quality": 9,
                "NameSeed": 22730,
                "Sector": 867,
                "LocationId": 26031
            },
            {
                "FactionId": 0,
                "BuildingType": 23,
                "Quality": 16,
                "NameSeed": 13877,
                "Sector": 869,
                "LocationId": 26031
            },
            {
                "FactionId": 0,
                "BuildingType": 15,
                "Quality": 6,
                "NameSeed": 20366,
                "Sector": 1138,
                "LocationId": 26031
            },
            {
                "NameSeed": 10943,
                "FactionId": 0,
                "Sector": 1745,
                "LocationId": 26031,
                "BuildingType": "House2",
                "Quality": 5
            },
            {
                "FactionId": 0,
                "BuildingType": 18,
                "Quality": 7,
                "NameSeed": 22049,
                "Sector": 1748,
                "LocationId": 26031
            },
            {
                "FactionId": 0,
                "BuildingType": 19,
                "Quality": 4,
                "NameSeed": 13830,
                "Sector": 1751,
                "LocationId": 26031
            },
            {
                "NameSeed": 2417,
                "FactionId": 0,
                "Sector": 1754,
                "LocationId": 26031,
                "BuildingType": "House2",
                "Quality": 4
            },
            {
                "NameSeed": 8020,
                "FactionId": 0,
                "Sector": 1757,
                "LocationId": 26031,
                "BuildingType": "House2",
                "Quality": 10
            },
            {
                "NameSeed": 35,
                "FactionId": 0,
                "Sector": 1760,
                "LocationId": 26031,
                "BuildingType": "House2",
                "Quality": 6
            },
            {
                "NameSeed": 25405,
                "FactionId": 0,
                "Sector": 1763,
                "LocationId": 26031,
                "BuildingType": "House2",
                "Quality": 5
            },
            {
                "NameSeed": 20012,
                "FactionId": 0,
                "Sector": 1766,
                "LocationId": 26031,
                "BuildingType": "House2",
                "Quality": 9
            },
            {
                "FactionId": 0,
                "BuildingType": 18,
                "Quality": 10,
                "NameSeed": 590,
                "Sector": 1769,
                "LocationId": 26031
            },
            {
                "NameSeed": 15427,
                "FactionId": 0,
                "Sector": 1772,
                "LocationId": 26031,
                "BuildingType": "House2",
                "Quality": 9
            },
            {
                "NameSeed": 8253,
                "FactionId": 0,
                "Sector": 1775,
                "LocationId": 26031,
                "BuildingType": "House2",
                "Quality": 6
            },
            {
                "FactionId": 0,
                "BuildingType": 19,
                "Quality": 4,
                "NameSeed": 28556,
                "Sector": 1778,
                "LocationId": 26031
            },
            {
                "NameSeed": 23001,
                "FactionId": 0,
                "Sector": 686,
                "LocationId": 26031,
                "BuildingType": "Library",
                "Quality": 20
            },
            {
                "NameSeed": 20715,
                "FactionId": 0,
                "Sector": 226,
                "LocationId": 26031,
                "BuildingType": "Armorer",
                "Quality": 18
            },
            {
                "NameSeed": 11385,
                "FactionId": 0,
                "Sector": 1781,
                "LocationId": 26031,
                "BuildingType": "House2",
                "Quality": 9
            },
            {
                "NameSeed": 19458,
                "FactionId": 0,
                "Sector": 1784,
                "LocationId": 26031,
                "BuildingType": "House2",
                "Quality": 4
            },
            {
                "NameSeed": 614,
                "FactionId": 0,
                "Sector": 1787,
                "LocationId": 26031,
                "BuildingType": "House2",
                "Quality": 4
            },
            {
                "NameSeed": 17614,
                "FactionId": 0,
                "Sector": 1790,
                "LocationId": 26031,
                "BuildingType": "House2",
                "Quality": 6
            },
            {
                "NameSeed": 2614,
                "FactionId": 0,
                "Sector": 1181,
                "LocationId": 26031,
                "BuildingType": "Tavern",
                "Quality": 7
            },
            {
                "NameSeed": 26165,
                "FactionId": 0,
                "Sector": 1793,
                "LocationId": 26031,
                "BuildingType": "House2",
                "Quality": 6
            },
            {
                "NameSeed": 26298,
                "FactionId": 0,
                "Sector": 1796,
                "LocationId": 26031,
                "BuildingType": "House2",
                "Quality": 6
            },
            {
                "NameSeed": 23339,
                "FactionId": 0,
                "Sector": 1799,
                "LocationId": 26031,
                "BuildingType": "House2",
                "Quality": 8
            },
            {
                "NameSeed": 27094,
                "FactionId": 0,
                "Sector": 1802,
                "LocationId": 26031,
                "BuildingType": "House2",
                "Quality": 5
            },
            {
                "NameSeed": 16096,
                "FactionId": 0,
                "Sector": 1805,
                "LocationId": 26031,
                "BuildingType": "House2",
                "Quality": 4
            },
            {
                "NameSeed": 9765,
                "FactionId": 0,
                "Sector": 1808,
                "LocationId": 26031,
                "BuildingType": "House2",
                "Quality": 8
            },
            {
                "NameSeed": 3753,
                "FactionId": 0,
                "Sector": 1811,
                "LocationId": 26031,
                "BuildingType": "House2",
                "Quality": 8
            },
            {
                "NameSeed": 1680,
                "FactionId": 0,
                "Sector": 1814,
                "LocationId": 26031,
                "BuildingType": "House2",
                "Quality": 6
            },
            {
                "NameSeed": 6450,
                "FactionId": 0,
                "Sector": 1817,
                "LocationId": 26031,
                "BuildingType": "House2",
                "Quality": 6
            },
            {
                "NameSeed": 20392,
                "FactionId": 0,
                "Sector": 1820,
                "LocationId": 26031,
                "BuildingType": "House2",
                "Quality": 6
            },
            {
                "NameSeed": 5508,
                "FactionId": 0,
                "Sector": 64,
                "LocationId": 26031,
                "BuildingType": "Bookseller",
                "Quality": 18
            },
            {
                "NameSeed": 17711,
                "FactionId": 0,
                "Sector": 71,
                "LocationId": 26031,
                "BuildingType": "Bookseller",
                "Quality": 10
            },
            {
                "FactionId": 0,
                "BuildingType": 15,
                "Quality": 18,
                "NameSeed": 4720,
                "Sector": 1288,
                "LocationId": 26031
            },
            {
                "NameSeed": 15075,
                "FactionId": 0,
                "Sector": 1823,
                "LocationId": 26031,
                "BuildingType": "House2",
                "Quality": 8
            },
            {
                "FactionId": 0,
                "BuildingType": 18,
                "Quality": 7,
                "NameSeed": 28369,
                "Sector": 1826,
                "LocationId": 26031
            },
            {
                "NameSeed": 16660,
                "FactionId": 0,
                "Sector": 1829,
                "LocationId": 26031,
                "BuildingType": "House3",
                "Quality": 6
            },
            {
                "NameSeed": 28695,
                "FactionId": 0,
                "Sector": 1832,
                "LocationId": 26031,
                "BuildingType": "House2",
                "Quality": 9
            },
            {
                "NameSeed": 6165,
                "FactionId": 0,
                "Sector": 1835,
                "LocationId": 26031,
                "BuildingType": "House2",
                "Quality": 6
            },
            {
                "NameSeed": 11561,
                "FactionId": 0,
                "Sector": 1838,
                "LocationId": 26031,
                "BuildingType": "House2",
                "Quality": 12
            },
            {
                "FactionId": 0,
                "BuildingType": 19,
                "Quality": 4,
                "NameSeed": 23089,
                "Sector": 1841,
                "LocationId": 26031
            },
            {
                "FactionId": 0,
                "BuildingType": 19,
                "Quality": 4,
                "NameSeed": 1777,
                "Sector": 1844,
                "LocationId": 26031
            },
            {
                "FactionId": 0,
                "BuildingType": 18,
                "Quality": 6,
                "NameSeed": 15516,
                "Sector": 1847,
                "LocationId": 26031
            },
            {
                "NameSeed": 4164,
                "FactionId": 0,
                "Sector": 1850,
                "LocationId": 26031,
                "BuildingType": "House2",
                "Quality": 9
            },
            {
                "NameSeed": 16241,
                "FactionId": 0,
                "Sector": 1853,
                "LocationId": 26031,
                "BuildingType": "House2",
                "Quality": 7
            },
            {
                "NameSeed": 1026,
                "FactionId": 0,
                "Sector": 1856,
                "LocationId": 26031,
                "BuildingType": "House2",
                "Quality": 8
            },
            {
                "NameSeed": 11129,
                "FactionId": 40,
                "Sector": 1332,
                "LocationId": 26031,
                "BuildingType": "GuildHall",
                "Quality": 5
            },
            {
                "NameSeed": 26252,
                "FactionId": 0,
                "Sector": 1859,
                "LocationId": 26031,
                "BuildingType": "House2",
                "Quality": 6
            },
            {
                "NameSeed": 17133,
                "FactionId": 0,
                "Sector": 1862,
                "LocationId": 26031,
                "BuildingType": "House2",
                "Quality": 6
            },
            {
                "NameSeed": 20031,
                "FactionId": 0,
                "Sector": 1865,
                "LocationId": 26031,
                "BuildingType": "House2",
                "Quality": 4
            },
            {
                "NameSeed": 2668,
                "FactionId": 0,
                "Sector": 1868,
                "LocationId": 26031,
                "BuildingType": "House2",
                "Quality": 5
            },
            {
                "NameSeed": 26181,
                "FactionId": 0,
                "Sector": 1871,
                "LocationId": 26031,
                "BuildingType": "House2",
                "Quality": 4
            },
            {
                "NameSeed": 10844,
                "FactionId": 0,
                "Sector": 1874,
                "LocationId": 26031,
                "BuildingType": "House3",
                "Quality": 6
            },
            {
                "NameSeed": 24917,
                "FactionId": 0,
                "Sector": 1877,
                "LocationId": 26031,
                "BuildingType": "House2",
                "Quality": 5
            },
            {
                "NameSeed": 23412,
                "FactionId": 0,
                "Sector": 1880,
                "LocationId": 26031,
                "BuildingType": "House2",
                "Quality": 8
            },
            {
                "NameSeed": 9074,
                "FactionId": 0,
                "Sector": 1883,
                "LocationId": 26031,
                "BuildingType": "House2",
                "Quality": 4
            },
            {
                "NameSeed": 17593,
                "FactionId": 0,
                "Sector": 1886,
                "LocationId": 26031,
                "BuildingType": "House2",
                "Quality": 6
            },
            {
                "NameSeed": 29204,
                "FactionId": 0,
                "Sector": 1889,
                "LocationId": 26031,
                "BuildingType": "House2",
                "Quality": 5
            },
            {
                "NameSeed": 8682,
                "FactionId": 0,
                "Sector": 1892,
                "LocationId": 26031,
                "BuildingType": "House2",
                "Quality": 5
            },
            {
                "NameSeed": 16063,
                "FactionId": 0,
                "Sector": 1895,
                "LocationId": 26031,
                "BuildingType": "House2",
                "Quality": 5
            },
            {
                "NameSeed": 798,
                "FactionId": 0,
                "Sector": 1898,
                "LocationId": 26031,
                "BuildingType": "House2",
                "Quality": 5
            },
            {
                "NameSeed": 14671,
                "FactionId": 0,
                "Sector": 1061,
                "LocationId": 26031,
                "BuildingType": "Armorer",
                "Quality": 13
            },
            {
                "NameSeed": 7939,
                "FactionId": 510,
                "Sector": 1066,
                "LocationId": 26031,
                "BuildingType": "Bookseller",
                "Quality": 17
            },
            {
                "NameSeed": 23654,
                "FactionId": 510,
                "Sector": 1071,
                "LocationId": 26031,
                "BuildingType": "ClothingStore",
                "Quality": 19
            },
            {
                "NameSeed": 3962,
                "FactionId": 510,
                "Sector": 1078,
                "LocationId": 26031,
                "BuildingType": "GeneralStore",
                "Quality": 10
            },
            {
                "NameSeed": 28170,
                "FactionId": 0,
                "Sector": 920,
                "LocationId": 26031,
                "BuildingType": "Alchemist",
                "Quality": 12
            },
            {
                "NameSeed": 3,
                "FactionId": 91,
                "Sector": 1094,
                "LocationId": 26031,
                "BuildingType": "WeaponSmith",
                "Quality": 16
            },
            {
                "FactionId": 510,
                "BuildingType": 15,
                "Quality": 9,
                "NameSeed": 20396,
                "Sector": 1301,
                "LocationId": 26031
            },
            {
                "NameSeed": 27640,
                "FactionId": 0,
                "Sector": 974,
                "LocationId": 26031,
                "BuildingType": "Alchemist",
                "Quality": 6
            },
            {
                "FactionId": 158,
                "BuildingType": 15,
                "Quality": 6,
                "NameSeed": 17324,
                "Sector": 1428,
                "LocationId": 26031
            },
            {
                "FactionId": 510,
                "BuildingType": 15,
                "Quality": 8,
                "NameSeed": 21596,
                "Sector": 1523,
                "LocationId": 26031
            },
            {
                "NameSeed": 21547,
                "FactionId": 510,
                "Sector": 1151,
                "LocationId": 26031,
                "BuildingType": "Bank",
                "Quality": 16
            },
            {
                "FactionId": 0,
                "BuildingType": 23,
                "Quality": 17,
                "NameSeed": 23972,
                "Sector": 1314,
                "LocationId": 26031
            },
            {
                "FactionId": 0,
                "BuildingType": 23,
                "Quality": 11,
                "NameSeed": 435,
                "Sector": 1316,
                "LocationId": 26031
            },
            {
                "FactionId": 0,
                "BuildingType": 23,
                "Quality": 13,
                "NameSeed": 2815,
                "Sector": 1318,
                "LocationId": 26031
            },
            {
                "FactionId": 0,
                "BuildingType": 23,
                "Quality": 11,
                "NameSeed": 27832,
                "Sector": 1320,
                "LocationId": 26031
            },
            {
                "FactionId": 0,
                "BuildingType": 15,
                "Quality": 9,
                "NameSeed": 801,
                "Sector": 1901,
                "LocationId": 26031
            },
            {
                "NameSeed": 20008,
                "FactionId": 0,
                "Sector": 1904,
                "LocationId": 26031,
                "BuildingType": "House2",
                "Quality": 8
            },
            {
                "NameSeed": 4302,
                "FactionId": 0,
                "Sector": 1907,
                "LocationId": 26031,
                "BuildingType": "House2",
                "Quality": 6
            },
            {
                "NameSeed": 2141,
                "FactionId": 0,
                "Sector": 1910,
                "LocationId": 26031,
                "BuildingType": "House2",
                "Quality": 2
            },
            {
                "NameSeed": 25526,
                "FactionId": 0,
                "Sector": 1913,
                "LocationId": 26031,
                "BuildingType": "House2",
                "Quality": 7
            },
            {
                "NameSeed": 14736,
                "FactionId": 0,
                "Sector": 1916,
                "LocationId": 26031,
                "BuildingType": "House2",
                "Quality": 8
            },
            {
                "NameSeed": 9919,
                "FactionId": 0,
                "Sector": 1919,
                "LocationId": 26031,
                "BuildingType": "House2",
                "Quality": 4
            },
            {
                "FactionId": 0,
                "BuildingType": 15,
                "Quality": 6,
                "NameSeed": 25805,
                "Sector": 1922,
                "LocationId": 26031
            },
            {
                "NameSeed": 23419,
                "FactionId": 0,
                "Sector": 1925,
                "LocationId": 26031,
                "BuildingType": "House2",
                "Quality": 8
            },
            {
                "FactionId": 0,
                "BuildingType": 23,
                "Quality": 6,
                "NameSeed": 31810,
                "Sector": 1323,
                "LocationId": 26031
            },
            {
                "FactionId": 0,
                "BuildingType": 23,
                "Quality": 10,
                "NameSeed": 24343,
                "Sector": 1325,
                "LocationId": 26031
            },
            {
                "FactionId": 0,
                "BuildingType": 23,
                "Quality": 8,
                "NameSeed": 29703,
                "Sector": 1327,
                "LocationId": 26031
            },
            {
                "FactionId": 0,
                "BuildingType": 23,
                "Quality": 17,
                "NameSeed": 10533,
                "Sector": 1329,
                "LocationId": 26031
            },
            {
                "FactionId": 0,
                "BuildingType": 15,
                "Quality": 10,
                "NameSeed": 21732,
                "Sector": 1928,
                "LocationId": 26031
            },
            {
                "NameSeed": 12470,
                "FactionId": 0,
                "Sector": 1931,
                "LocationId": 26031,
                "BuildingType": "House2",
                "Quality": 10
            },
            {
                "NameSeed": 27003,
                "FactionId": 0,
                "Sector": 1934,
                "LocationId": 26031,
                "BuildingType": "House2",
                "Quality": 4
            },
            {
                "NameSeed": 13674,
                "FactionId": 0,
                "Sector": 1937,
                "LocationId": 26031,
                "BuildingType": "House2",
                "Quality": 6
            },
            {
                "NameSeed": 10746,
                "FactionId": 0,
                "Sector": 1940,
                "LocationId": 26031,
                "BuildingType": "House2",
                "Quality": 8
            },
            {
                "NameSeed": 5690,
                "FactionId": 0,
                "Sector": 1943,
                "LocationId": 26031,
                "BuildingType": "House2",
                "Quality": 8
            },
            {
                "NameSeed": 28124,
                "FactionId": 0,
                "Sector": 1946,
                "LocationId": 26031,
                "BuildingType": "House2",
                "Quality": 4
            },
            {
                "NameSeed": 6751,
                "FactionId": 0,
                "Sector": 1949,
                "LocationId": 26031,
                "BuildingType": "House2",
                "Quality": 6
            },
            {
                "NameSeed": 12944,
                "FactionId": 0,
                "Sector": 1952,
                "LocationId": 26031,
                "BuildingType": "House5",
                "Quality": 10
            },
            {
                "NameSeed": 461,
                "FactionId": 0,
                "Sector": 1955,
                "LocationId": 26031,
                "BuildingType": "House5",
                "Quality": 0
            },
            {
                "NameSeed": 1336,
                "FactionId": 0,
                "Sector": 1958,
                "LocationId": 26031,
                "BuildingType": "House5",
                "Quality": 0
            },
            {
                "NameSeed": 20498,
                "FactionId": 0,
                "Sector": 1961,
                "LocationId": 26031,
                "BuildingType": "House5",
                "Quality": 0
            },
            {
                "NameSeed": 29912,
                "FactionId": 0,
                "Sector": 1964,
                "LocationId": 26031,
                "BuildingType": "House5",
                "Quality": 0
            },
            {
                "NameSeed": 12991,
                "FactionId": 0,
                "Sector": 1967,
                "LocationId": 26031,
                "BuildingType": "House5",
                "Quality": 10
            },
            {
                "NameSeed": 520,
                "FactionId": 0,
                "Sector": 1970,
                "LocationId": 26031,
                "BuildingType": "House5",
                "Quality": 0
            },
            {
                "NameSeed": 1717,
                "FactionId": 0,
                "Sector": 1973,
                "LocationId": 26031,
                "BuildingType": "House5",
                "Quality": 0
            },
            {
                "NameSeed": 16517,
                "FactionId": 0,
                "Sector": 1976,
                "LocationId": 26031,
                "BuildingType": "House5",
                "Quality": 0
            },
            {
                "NameSeed": 21329,
                "FactionId": 0,
                "Sector": 1979,
                "LocationId": 26031,
                "BuildingType": "House5",
                "Quality": 0
            },
            {
                "NameSeed": 19401,
                "FactionId": 0,
                "Sector": 1982,
                "LocationId": 26031,
                "BuildingType": "House5",
                "Quality": 0
            },
            {
                "NameSeed": 27949,
                "FactionId": 0,
                "Sector": 1985,
                "LocationId": 26031,
                "BuildingType": "House5",
                "Quality": 5
            },
            {
                "NameSeed": 28533,
                "FactionId": 0,
                "Sector": 1988,
                "LocationId": 26031,
                "BuildingType": "House5",
                "Quality": 0
            },
            {
                "NameSeed": 15772,
                "FactionId": 0,
                "Sector": 1991,
                "LocationId": 26031,
                "BuildingType": "House5",
                "Quality": 0
            },
            {
                "NameSeed": 13685,
                "FactionId": 0,
                "Sector": 1994,
                "LocationId": 26031,
                "BuildingType": "House5",
                "Quality": 0
            },
            {
                "NameSeed": 2561,
                "FactionId": 108,
                "Sector": 108,
                "LocationId": 26031,
                "BuildingType": "House2",
                "Quality": 9
            },
            {
                "FactionId": 0,
                "BuildingType": 15,
                "Quality": 6,
                "NameSeed": 26098,
                "Sector": 1997,
                "LocationId": 26031
            },
            {
                "NameSeed": 29592,
                "FactionId": 0,
                "Sector": 2000,
                "LocationId": 26031,
                "BuildingType": "House2",
                "Quality": 5
            },
            {
                "NameSeed": 7911,
                "FactionId": 0,
                "Sector": 2003,
                "LocationId": 26031,
                "BuildingType": "House3",
                "Quality": 6
            },
            {
                "NameSeed": 5336,
                "FactionId": 0,
                "Sector": 2006,
                "LocationId": 26031,
                "BuildingType": "House2",
                "Quality": 5
            },
            {
                "NameSeed": 29932,
                "FactionId": 0,
                "Sector": 2009,
                "LocationId": 26031,
                "BuildingType": "House2",
                "Quality": 6
            },
            {
                "NameSeed": 23952,
                "FactionId": 0,
                "Sector": 2012,
                "LocationId": 26031,
                "BuildingType": "House2",
                "Quality": 8
            },
            {
                "NameSeed": 13274,
                "FactionId": 0,
                "Sector": 2015,
                "LocationId": 26031,
                "BuildingType": "House2",
                "Quality": 6
            },
            {
                "NameSeed": 2137,
                "FactionId": 0,
                "Sector": 2018,
                "LocationId": 26031,
                "BuildingType": "House2",
                "Quality": 5
            },
            {
                "NameSeed": 14934,
                "FactionId": 0,
                "Sector": 2021,
                "LocationId": 26031,
                "BuildingType": "House2",
                "Quality": 5
            },
            {
                "FactionId": 0,
                "BuildingType": 19,
                "Quality": 4,
                "NameSeed": 25048,
                "Sector": 2024,
                "LocationId": 26031
            },
            {
                "NameSeed": 7875,
                "FactionId": 0,
                "Sector": 2027,
                "LocationId": 26031,
                "BuildingType": "House2",
                "Quality": 5
            },
            {
                "NameSeed": 11172,
                "FactionId": 0,
                "Sector": 2030,
                "LocationId": 26031,
                "BuildingType": "House2",
                "Quality": 6
            },
            {
                "NameSeed": 4818,
                "FactionId": 0,
                "Sector": 2033,
                "LocationId": 26031,
                "BuildingType": "House2",
                "Quality": 8
            },
            {
                "NameSeed": 22077,
                "FactionId": 0,
                "Sector": 2036,
                "LocationId": 26031,
                "BuildingType": "House2",
                "Quality": 6
            },
            {
                "NameSeed": 7337,
                "FactionId": 0,
                "Sector": 2039,
                "LocationId": 26031,
                "BuildingType": "House2",
                "Quality": 5
            },
            {
                "NameSeed": 14864,
                "FactionId": 0,
                "Sector": 2042,
                "LocationId": 26031,
                "BuildingType": "House2",
                "Quality": 6
            },
            {
                "NameSeed": 4732,
                "FactionId": 0,
                "Sector": 2045,
                "LocationId": 26031,
                "BuildingType": "House2",
                "Quality": 12
            },
            {
                "NameSeed": 20546,
                "FactionId": 0,
                "Sector": 2048,
                "LocationId": 26031,
                "BuildingType": "House2",
                "Quality": 4
            },
            {
                "NameSeed": 19453,
                "FactionId": 0,
                "Sector": 2051,
                "LocationId": 26031,
                "BuildingType": "House2",
                "Quality": 8
            },
            {
                "NameSeed": 24141,
                "FactionId": 0,
                "Sector": 2054,
                "LocationId": 26031,
                "BuildingType": "House2",
                "Quality": 8
            },
            {
                "NameSeed": 11964,
                "FactionId": 0,
                "Sector": 2057,
                "LocationId": 26031,
                "BuildingType": "House2",
                "Quality": 8
            },
            {
                "NameSeed": 24474,
                "FactionId": 0,
                "Sector": 2060,
                "LocationId": 26031,
                "BuildingType": "House2",
                "Quality": 6
            },
            {
                "NameSeed": 5915,
                "FactionId": 0,
                "Sector": 2063,
                "LocationId": 26031,
                "BuildingType": "House2",
                "Quality": 6
            },
            {
                "NameSeed": 12090,
                "FactionId": 0,
                "Sector": 2066,
                "LocationId": 26031,
                "BuildingType": "House2",
                "Quality": 2
            },
            {
                "NameSeed": 29566,
                "FactionId": 0,
                "Sector": 2069,
                "LocationId": 26031,
                "BuildingType": "House2",
                "Quality": 6
            },
            {
                "NameSeed": 15969,
                "FactionId": 0,
                "Sector": 2072,
                "LocationId": 26031,
                "BuildingType": "House2",
                "Quality": 7
            },
            {
                "NameSeed": 29905,
                "FactionId": 0,
                "Sector": 1089,
                "LocationId": 26031,
                "BuildingType": "Alchemist",
                "Quality": 17
            },
            {
                "NameSeed": 12171,
                "FactionId": 0,
                "Sector": 2075,
                "LocationId": 26031,
                "BuildingType": "House2",
                "Quality": 7
            },
            {
                "NameSeed": 9317,
                "FactionId": 0,
                "Sector": 2078,
                "LocationId": 26031,
                "BuildingType": "House2",
                "Quality": 2
            },
            {
                "NameSeed": 5284,
                "FactionId": 0,
                "Sector": 2081,
                "LocationId": 26031,
                "BuildingType": "House2",
                "Quality": 7
            },
            {
                "NameSeed": 8304,
                "FactionId": 0,
                "Sector": 2084,
                "LocationId": 26031,
                "BuildingType": "House2",
                "Quality": 7
            },
            {
                "NameSeed": 29187,
                "FactionId": 0,
                "Sector": 2087,
                "LocationId": 26031,
                "BuildingType": "House2",
                "Quality": 7
            },
            {
                "FactionId": 0,
                "BuildingType": 15,
                "Quality": 15,
                "NameSeed": 19226,
                "Sector": 2090,
                "LocationId": 26031
            },
            {
                "NameSeed": 6442,
                "FactionId": 0,
                "Sector": 2093,
                "LocationId": 26031,
                "BuildingType": "House2",
                "Quality": 6
            },
            {
                "NameSeed": 20838,
                "FactionId": 0,
                "Sector": 193,
                "LocationId": 26031,
                "BuildingType": "HouseForSale",
                "Quality": 17
            },
            {
                "NameSeed": 1799,
                "FactionId": 0,
                "Sector": 1121,
                "LocationId": 26031,
                "BuildingType": "Alchemist",
                "Quality": 20
            },
            {
                "NameSeed": 14972,
                "FactionId": 0,
                "Sector": 2096,
                "LocationId": 26031,
                "BuildingType": "House5",
                "Quality": 10
            },
            {
                "NameSeed": 14051,
                "FactionId": 0,
                "Sector": 2099,
                "LocationId": 26031,
                "BuildingType": "House5",
                "Quality": 10
            },
            {
                "FactionId": 0,
                "BuildingType": 23,
                "Quality": 11,
                "NameSeed": 28197,
                "Sector": 1571,
                "LocationId": 26031
            },
            {
                "FactionId": 0,
                "BuildingType": 23,
                "Quality": 20,
                "NameSeed": 7557,
                "Sector": 1573,
                "LocationId": 26031
            },
            {
                "FactionId": 0,
                "BuildingType": 23,
                "Quality": 19,
                "NameSeed": 5617,
                "Sector": 1575,
                "LocationId": 26031
            },
            {
                "FactionId": 0,
                "BuildingType": 23,
                "Quality": 10,
                "NameSeed": 21706,
                "Sector": 1577,
                "LocationId": 26031
            },
            {
                "FactionId": 0,
                "BuildingType": 23,
                "Quality": 19,
                "NameSeed": 2841,
                "Sector": 1580,
                "LocationId": 26031
            },
            {
                "FactionId": 0,
                "BuildingType": 23,
                "Quality": 11,
                "NameSeed": 5959,
                "Sector": 1583,
                "LocationId": 26031
            },
            {
                "FactionId": 0,
                "BuildingType": 23,
                "Quality": 5,
                "NameSeed": 13796,
                "Sector": 1585,
                "LocationId": 26031
            },
            {
                "FactionId": 0,
                "BuildingType": 23,
                "Quality": 5,
                "NameSeed": 19861,
                "Sector": 1587,
                "LocationId": 26031
            },
            {
                "FactionId": 0,
                "BuildingType": 23,
                "Quality": 16,
                "NameSeed": 21510,
                "Sector": 1589,
                "LocationId": 26031
            },
            {
                "FactionId": 0,
                "BuildingType": 23,
                "Quality": 5,
                "NameSeed": 22896,
                "Sector": 1592,
                "LocationId": 26031
            },
            {
                "FactionId": 0,
                "BuildingType": 23,
                "Quality": 9,
                "NameSeed": 15878,
                "Sector": 1594,
                "LocationId": 26031
            },
            {
                "FactionId": 0,
                "BuildingType": 23,
                "Quality": 17,
                "NameSeed": 24698,
                "Sector": 1596,
                "LocationId": 26031
            },
            {
                "FactionId": 0,
                "BuildingType": 23,
                "Quality": 9,
                "NameSeed": 9808,
                "Sector": 1598,
                "LocationId": 26031
            },
            {
                "NameSeed": 15981,
                "FactionId": 0,
                "Sector": 2102,
                "LocationId": 26031,
                "BuildingType": "House2",
                "Quality": 18
            },
            {
                "FactionId": 0,
                "BuildingType": 23,
                "Quality": 17,
                "NameSeed": 1717,
                "Sector": 1601,
                "LocationId": 26031
            },
            {
                "FactionId": 0,
                "BuildingType": 23,
                "Quality": 13,
                "NameSeed": 11801,
                "Sector": 1603,
                "LocationId": 26031
            },
            {
                "FactionId": 0,
                "BuildingType": 23,
                "Quality": 17,
                "NameSeed": 21694,
                "Sector": 1605,
                "LocationId": 26031
            },
            {
                "FactionId": 0,
                "BuildingType": 23,
                "Quality": 17,
                "NameSeed": 27639,
                "Sector": 1607,
                "LocationId": 26031
            },
            {
                "FactionId": 0,
                "BuildingType": 23,
                "Quality": 8,
                "NameSeed": 17866,
                "Sector": 1610,
                "LocationId": 26031
            },
            {
                "FactionId": 0,
                "BuildingType": 23,
                "Quality": 10,
                "NameSeed": 16444,
                "Sector": 1612,
                "LocationId": 26031
            },
            {
                "FactionId": 0,
                "BuildingType": 23,
                "Quality": 5,
                "NameSeed": 14690,
                "Sector": 1614,
                "LocationId": 26031
            },
            {
                "FactionId": 0,
                "BuildingType": 23,
                "Quality": 5,
                "NameSeed": 4886,
                "Sector": 1616,
                "LocationId": 26031
            },
            {
                "NameSeed": 9420,
                "FactionId": 0,
                "Sector": 2105,
                "LocationId": 26031,
                "BuildingType": "House2",
                "Quality": 5
            },
            {
                "NameSeed": 266,
                "FactionId": 0,
                "Sector": 2108,
                "LocationId": 26031,
                "BuildingType": "House2",
                "Quality": 5
            },
            {
                "NameSeed": 17266,
                "FactionId": 0,
                "Sector": 2111,
                "LocationId": 26031,
                "BuildingType": "House2",
                "Quality": 7
            },
            {
                "NameSeed": 14224,
                "FactionId": 0,
                "Sector": 2114,
                "LocationId": 26031,
                "BuildingType": "House2",
                "Quality": 5
            },
            {
                "NameSeed": 26884,
                "FactionId": 0,
                "Sector": 2117,
                "LocationId": 26031,
                "BuildingType": "House2",
                "Quality": 4
            },
            {
                "NameSeed": 12892,
                "FactionId": 0,
                "Sector": 2120,
                "LocationId": 26031,
                "BuildingType": "House2",
                "Quality": 5
            },
            {
                "NameSeed": 14101,
                "FactionId": 0,
                "Sector": 2123,
                "LocationId": 26031,
                "BuildingType": "House2",
                "Quality": 6
            },
            {
                "FactionId": 0,
                "BuildingType": 15,
                "Quality": 7,
                "NameSeed": 16787,
                "Sector": 2126,
                "LocationId": 26031
            },
            {
                "FactionId": 0,
                "BuildingType": 15,
                "Quality": 3,
                "NameSeed": 8068,
                "Sector": 2129,
                "LocationId": 26031
            },
            {
                "FactionId": 0,
                "BuildingType": 15,
                "Quality": 15,
                "NameSeed": 6772,
                "Sector": 2132,
                "LocationId": 26031
            },
            {
                "FactionId": 0,
                "BuildingType": 23,
                "Quality": 14,
                "NameSeed": 17630,
                "Sector": 1619,
                "LocationId": 26031
            },
            {
                "FactionId": 0,
                "BuildingType": 23,
                "Quality": 18,
                "NameSeed": 22631,
                "Sector": 1621,
                "LocationId": 26031
            },
            {
                "FactionId": 0,
                "BuildingType": 23,
                "Quality": 9,
                "NameSeed": 8355,
                "Sector": 1623,
                "LocationId": 26031
            },
            {
                "FactionId": 0,
                "BuildingType": 23,
                "Quality": 16,
                "NameSeed": 30053,
                "Sector": 1625,
                "LocationId": 26031
            },
            {
                "FactionId": 0,
                "BuildingType": 23,
                "Quality": 7,
                "NameSeed": 11548,
                "Sector": 1628,
                "LocationId": 26031
            }
        ],
        "ExteriorData": {
            "AnotherName": "Damenaweyn",
            "MapId": 381922,
            "LocationId": 0,
            "Width": 7,
            "Height": 6,
            "PortTownAndUnknown": 0,
            "BlockNames": [
                "FARMAA08.RMB",
                "WALLAA02.FARMAA10.RMB",
                "WALLAA06.FARMAA12.RMB",
                "WALLAA10.TVRNAS00.RMB",
                "WALLAA06.FARMAA05.RMB",
                "WALLAA06.FARMAA11.RMB",
                "WALLAA03.FARMAA04.RMB",
                "WALLAA02.FARMAA02.RMB",
                "WALLAA13.FARMAA05.RMB",
                "TVRNAL03.RMB",
                "TEMPAAB0.RMB",
                "GEMSAL01.RMB",
                "THIEAL00.RMB",
                "WALLAA05.FARMAA12.RMB",
                "WALLAA07.FARMAA10.RMB",
                "ARMRAL00.RMB",
                "FIGHAA00.RMB",
                "GENRAL00.RMB",
                "PALAAA00.RMB",
                "KSCAAL01.RMB",
                "WALLAA05.FARMAA12.RMB",
                "WALLAA07.FARMAA11.RMB",
                "LIBRAL02.RMB",
                "ARMRAL00.RMB",
                "BOOKAL02.RMB",
                "MAGEAA10.RMB",
                "MARKAA00.RMB",
                "WALLAA09.TVRNAS01.RMB",
                "WALLAA11.TVRNAS00.RMB",
                "GRVEAL25.RMB",
                "DARKAA01.RMB",
                "ALCHAL01.RMB",
                "WALLAA14.FARMAA12.RMB",
                "WALLAA04.FARMAA13.RMB",
                "WALLAA01.FARMAA13.RMB",
                "WALLAA00.FARMAA03.RMB",
                "WALLAA04.FARMAA10.RMB",
                "WALLAA08.TVRNAS00.RMB",
                "WALLAA04.FARMAA10.RMB",
                "WALLAA01.FARMAA11.RMB",
                "FARMAA12.RMB",
                "FARMAA10.RMB"
            ]
        }
    },
    "Dungeon": {
        "RecordElement": {
            "Header": {
                "X": 0,
                "Y": 0,
                "IsExterior": 0,
                "Unknown2": 0,
                "LocationId": 0,
                "IsInterior": 0,
                "ExteriorLocationId": 0,
                "LocationName": null
            }
        },
        "Header": {
            "BlockCount": 0
        },
        "Blocks": null
    },
    "Climate": {
        "WorldClimate": 227,
        "ClimateType": "Swamp",
        "NatureSet": "Nature_RainForest",
        "GroundArchive": 402,
        "NatureArchive": 500,
        "SkyBase": 24,
        "People": "Redguard",
        "Names": "Nord"
    },
    "Politic": 179,
    "RegionIndex": 51,
    "LocationIndex": 848
}